railguns/__init__.py
railguns/urls.py
railguns/cloudfile/__init__.py
railguns/cloudfile/fields.py
railguns/cloudfile/widgets.py
railguns/django/__init__.py
railguns/django/generics.py
railguns/django/contrib/__init__.py
railguns/django/contrib/admin.py
railguns/django/contrib/auth/__init__.py
railguns/django/contrib/auth/backends.py
railguns/django/db/__init__.py
railguns/django/db/models.py
railguns/django/db/utils.py
railguns/django/utils/__init__.py
railguns/django/utils/html.py
railguns/django/utils/translation.py
railguns/rest_framework/__init__.py
railguns/rest_framework/generics.py
railguns/rest_framework/mixins.py
railguns/rest_framework/pagination.py
railguns/rest_framework/permissions.py
railguns/rest_framework/serializers.py
railguns/rest_framework/utils.py
railguns/rest_framework/views.py
railguns/rest_framework/schemas/__init__.py
railguns/rest_framework/schemas/openapi.py
railguns/static/cloudfile/js/scripts.js
railguns/static/railguns/es2015/mixins.js
railguns/static/railguns/es2015/vendor.js
railguns/static/railguns/es2015/components/weui-components.js
railguns/static/railguns/es2015/util/http-utils.js
railguns/static/railguns/js/mixins.js
railguns/static/railguns/js/vendor.js
railguns/static/railguns/js/components/weui-components.js
railguns/static/railguns/js/util/http-utils.js
railguns/templates/railguns/base.html
railguns/templates/railguns/base_quick.html
railguns/templates/railguns/ui/base.html
railguns/templates/railguns/ui/detail.html
railguns/templates/railguns/ui/list.html
railguns/tools/__init__.py
railguns/tools/utils.py
railguns-0.200.dist-info/METADATA
railguns-0.200.dist-info/WHEEL
railguns-0.200.dist-info/licenses/LICENSE
railguns-0.200.dist-info/RECORD
