Metadata-Version: 2.4
Name: railguns
Version: 0.200
Summary: Only My Railgun
Project-URL: Homepage, https://github.com/nyssance/railguns
Project-URL: Documentation, https://github.com/nyssance/railguns
Project-URL: Repository, https://github.com/nyssance/railguns.git
Project-URL: Issues, https://github.com/nyssance/railguns/issues
Project-URL: Changelog, https://github.com/nyssance/railguns/blob/main/CHANGELOG.md
Author-email: NY  <nyssance@icloud.com>
License: MIT License
License-File: LICENSE
Keywords: django,railguns
Classifier: Development Status :: 5 - Production/Stable
Classifier: Environment :: Web Environment
Classifier: Framework :: Django :: 6.0
Classifier: Intended Audience :: Developers
Classifier: License :: OSI Approved :: MIT License
Classifier: Operating System :: OS Independent
Classifier: Programming Language :: Python :: 3.14
Classifier: Topic :: Internet :: WWW/HTTP
Requires-Python: >=3.14
Requires-Dist: django-ckeditor-5==0.2.18
Requires-Dist: django-filter==25.2
Requires-Dist: django-htmlmin==0.11.0
Requires-Dist: django[argon2]==6.0
Requires-Dist: djangorestframework-simplejwt==5.5.1
Requires-Dist: djangorestframework==3.16.1
Requires-Dist: gunicorn==23.0.0
Requires-Dist: mysql-connector-python==9.5.0
Requires-Dist: redis==7.1.0
Requires-Dist: uvicorn==0.38.0
Provides-Extra: cli
Requires-Dist: fabric; extra == 'cli'
Requires-Dist: rich; extra == 'cli'
Provides-Extra: test
Requires-Dist: pytest-cov[all]; extra == 'test'
Requires-Dist: pytest>8.0.0; extra == 'test'
